servy/__init__.py
servy/client.py
servy/exc.py
servy/proto.py
servy/server.py
servy-0.2.4.dist-info/DESCRIPTION.rst
servy-0.2.4.dist-info/METADATA
servy-0.2.4.dist-info/metadata.json
servy-0.2.4.dist-info/RECORD
servy-0.2.4.dist-info/top_level.txt
servy-0.2.4.dist-info/WHEEL
