Metadata-Version: 2.0
Name: servy
Version: 0.2.4
Summary: Pythonic RPC over RESTful protocol
Home-page: https://github.com/mylokin/servy
Author: Andrey Gubarev
Author-email: mylokin@me.com
License: MIT
Keywords: rpc
Platform: UNKNOWN
Classifier: Development Status :: 4 - Beta
Classifier: Intended Audience :: Developers
Classifier: Operating System :: OS Independent
Classifier: License :: OSI Approved :: MIT License
Classifier: Programming Language :: Python
Classifier: Programming Language :: Python :: 2.7
Requires-Dist: WebOb (==1.4)
